exonware/xschema/version.py
exonware/xwschema/__init__.py
exonware/xwschema/base.py
exonware/xwschema/builder.py
exonware/xwschema/config.py
exonware/xwschema/contracts.py
exonware/xwschema/defs.py
exonware/xwschema/engine.py
exonware/xwschema/errors.py
exonware/xwschema/facade.py
exonware/xwschema/generator.py
exonware/xwschema/validator.py
exonware/xwschema/version.py
exonware/xwschema/formats/__init__.py
exonware/xwschema/formats/base.py
exonware/xwschema/formats/schema/__init__.py
exonware/xwschema/formats/schema/avro_schema.py
exonware/xwschema/formats/schema/graphql_schema.py
exonware/xwschema/formats/schema/json_schema.py
exonware/xwschema/formats/schema/openapi_schema.py
exonware/xwschema/formats/schema/protobuf_schema.py
exonware/xwschema/formats/schema/swagger_schema.py
exonware/xwschema/formats/schema/wsdl_schema.py
exonware/xwschema/formats/schema/xsd_schema.py
exonware/xwschema/registry/__init__.py
exonware/xwschema/registry/base.py
exonware/xwschema/registry/defs.py
exonware/xwschema/registry/errors.py
exonware/xwschema/registry/schema_registry.py
exonware_xwschema-0.0.1.2.dist-info/METADATA
exonware_xwschema-0.0.1.2.dist-info/WHEEL
exonware_xwschema-0.0.1.2.dist-info/licenses/LICENSE
exonware_xwschema-0.0.1.2.dist-info/RECORD
