Metadata-Version: 2.4
Name: exonware-xwschema
Version: 0.0.1.2
Summary: Schema validation and data structure definition library
Project-URL: Homepage, https://exonware.com
Project-URL: Repository, https://github.com/exonware/xwschema
Project-URL: Documentation, https://github.com/exonware/xwschema#readme
Author-email: "Eng. Muhammad AlShehri" <connect@exonware.com>
License: MIT
License-File: LICENSE
Keywords: data-types,definition,exonware,schema,structure,validation
Classifier: Development Status :: 3 - Alpha
Classifier: Intended Audience :: Developers
Classifier: License :: OSI Approved :: MIT License
Classifier: Operating System :: OS Independent
Classifier: Programming Language :: Python :: 3
Classifier: Programming Language :: Python :: 3.12
Classifier: Topic :: Software Development :: Libraries :: Python Modules
Requires-Python: >=3.12
Requires-Dist: boto3>=1.26.0
Requires-Dist: exonware-xwsystem
Requires-Dist: requests>=2.28.0
Provides-Extra: dev
Requires-Dist: black>=23.0.0; extra == 'dev'
Requires-Dist: isort>=5.12.0; extra == 'dev'
Requires-Dist: mypy>=1.0.0; extra == 'dev'
Requires-Dist: pytest-asyncio>=0.21.0; extra == 'dev'
Requires-Dist: pytest-cov>=4.0.0; extra == 'dev'
Requires-Dist: pytest>=7.0.0; extra == 'dev'
Provides-Extra: full
Requires-Dist: exonware-xwsystem[full]; extra == 'full'
Provides-Extra: lazy
Requires-Dist: exonware-xwsystem[lazy]; extra == 'lazy'
